[
  {
    "model": "bucket.tooth",
    "pk": 1,
    "fields": {
      "name": "d-series100-sharp",
      "title": "D系列 尖 100",
      "description": "D系列 尖 100 型号描述",
      "image": "/uploads/demo_bucket.jpg",
      "image_src": "http://sd-get.com/home/2/c/sdvaqx/resource/2020/11/03/5fa0f5b0bbf9e.jpg",
      "category": 1
    }
  },
  {
    "model": "bucket.tooth",
    "pk": 2,
    "fields": {
      "name": "d-series200-sharp",
      "title": "D系列 尖 200",
      "description": "D系列 尖 200 型号描述",
      "image": "/uploads/demo_bucket.jpg",
      "image_src": "http://sd-get.com/home/2/c/sdvaqx/resource/2020/11/03/5fa0f5b0bbf9e.jpg",
      "category": 1
    }
  },
  {
    "model": "bucket.tooth",
    "pk": 3,
    "fields": {
      "name": "d-series100-flat",
      "title": "D系列 平 100",
      "description": "D系列 平 100 型号描述",
      "image": "/uploads/demo_bucket.jpg",
      "image_src": "http://sd-get.com/home/2/c/sdvaqx/resource/2020/11/03/5fa0f5b0bbf9e.jpg",
      "category": 1
    }
  },
  {
    "model": "bucket.tooth",
    "pk": 4,
    "fields": {
      "name": "d-series200-flat",
      "title": "D系列 平 200",
      "description": "D系列 平 200 型号描述",
      "image": "/uploads/demo_bucket.jpg",
      "image_src": "http://sd-get.com/home/2/c/sdvaqx/resource/2020/11/03/5fa0f5b0bbf9e.jpg",
      "category": 1
    }
  },
  {
    "model": "bucket.tooth",
    "pk": 5,
    "fields": {
      "name": "dayu220100-sharp",
      "title": "大宇220 尖 100",
      "description": "大宇220 尖 100 型号描述",
      "image": "/uploads/demo_bucket.jpg",
      "image_src": "http://sd-get.com/home/2/c/sdvaqx/resource/2020/11/03/5fa0f5b0bbf9e.jpg",
      "category": 2
    }
  },
  {
    "model": "bucket.tooth",
    "pk": 6,
    "fields": {
      "name": "dayu220200-sharp",
      "title": "大宇220 尖 200",
      "description": "大宇220 尖 200 型号描述",
      "image": "/uploads/demo_bucket.jpg",
      "image_src": "http://sd-get.com/home/2/c/sdvaqx/resource/2020/11/03/5fa0f5b0bbf9e.jpg",
      "category": 2
    }
  },
  {
    "model": "bucket.tooth",
    "pk": 7,
    "fields": {
      "name": "dayu220100-flat",
      "title": "大宇220 平 100",
      "description": "大宇220 平 100 型号描述",
      "image": "/uploads/demo_bucket.jpg",
      "image_src": "http://sd-get.com/home/2/c/sdvaqx/resource/2020/11/03/5fa0f5b0bbf9e.jpg",
      "category": 2
    }
  },
  {
    "model": "bucket.tooth",
    "pk": 8,
    "fields": {
      "name": "dayu220200-flat",
      "title": "大宇220 平 200",
      "description": "大宇220 平 200 型号描述",
      "image": "/uploads/demo_bucket.jpg",
      "image_src": "http://sd-get.com/home/2/c/sdvaqx/resource/2020/11/03/5fa0f5b0bbf9e.jpg",
      "category": 2
    }
  },
  {
    "model": "bucket.tooth",
    "pk": 9,
    "fields": {
      "name": "dayu280100-sharp",
      "title": "大宇280 尖 100",
      "description": "大宇280 尖 100 型号描述",
      "image": "/uploads/demo_bucket.jpg",
      "image_src": "http://sd-get.com/home/2/c/sdvaqx/resource/2020/11/03/5fa0f5b0bbf9e.jpg",
      "category": 3
    }
  },
  {
    "model": "bucket.tooth",
    "pk": 10,
    "fields": {
      "name": "dayu280200-sharp",
      "title": "大宇280 尖 200",
      "description": "大宇280 尖 200 型号描述",
      "image": "/uploads/demo_bucket.jpg",
      "image_src": "http://sd-get.com/home/2/c/sdvaqx/resource/2020/11/03/5fa0f5b0bbf9e.jpg",
      "category": 3
    }
  },
  {
    "model": "bucket.tooth",
    "pk": 11,
    "fields": {
      "name": "dayu280100-flat",
      "title": "大宇280 平 100",
      "description": "大宇280 平 100 型号描述",
      "image": "/uploads/demo_bucket.jpg",
      "image_src": "http://sd-get.com/home/2/c/sdvaqx/resource/2020/11/03/5fa0f5b0bbf9e.jpg",
      "category": 3
    }
  },
  {
    "model": "bucket.tooth",
    "pk": 12,
    "fields": {
      "name": "dayu280200-flat",
      "title": "大宇280 平 200",
      "description": "大宇280 平 200 型号描述",
      "image": "/uploads/demo_bucket.jpg",
      "image_src": "http://sd-get.com/home/2/c/sdvaqx/resource/2020/11/03/5fa0f5b0bbf9e.jpg",
      "category": 3
    }
  },
  {
    "model": "bucket.tooth",
    "pk": 13,
    "fields": {
      "name": "dayu300100-sharp",
      "title": "大宇300 尖 100",
      "description": "大宇300 尖 100 型号描述",
      "image": "/uploads/demo_bucket.jpg",
      "image_src": "http://sd-get.com/home/2/c/sdvaqx/resource/2020/11/03/5fa0f5b0bbf9e.jpg",
      "category": 4
    }
  },
  {
    "model": "bucket.tooth",
    "pk": 14,
    "fields": {
      "name": "dayu300200-sharp",
      "title": "大宇300 尖 200",
      "description": "大宇300 尖 200 型号描述",
      "image": "/uploads/demo_bucket.jpg",
      "image_src": "http://sd-get.com/home/2/c/sdvaqx/resource/2020/11/03/5fa0f5b0bbf9e.jpg",
      "category": 4
    }
  },
  {
    "model": "bucket.tooth",
    "pk": 15,
    "fields": {
      "name": "dayu300100-flat",
      "title": "大宇300 平 100",
      "description": "大宇300 平 100 型号描述",
      "image": "/uploads/demo_bucket.jpg",
      "image_src": "http://sd-get.com/home/2/c/sdvaqx/resource/2020/11/03/5fa0f5b0bbf9e.jpg",
      "category": 4
    }
  },
  {
    "model": "bucket.tooth",
    "pk": 16,
    "fields": {
      "name": "dayu300200-flat",
      "title": "大宇300 平 200",
      "description": "大宇300 平 200 型号描述",
      "image": "/uploads/demo_bucket.jpg",
      "image_src": "http://sd-get.com/home/2/c/sdvaqx/resource/2020/11/03/5fa0f5b0bbf9e.jpg",
      "category": 4
    }
  },
  {
    "model": "bucket.tooth",
    "pk": 17,
    "fields": {
      "name": "dayu360100-sharp",
      "title": "大宇360 尖 100",
      "description": "大宇360 尖 100 型号描述",
      "image": "/uploads/demo_bucket.jpg",
      "image_src": "http://sd-get.com/home/2/c/sdvaqx/resource/2020/11/03/5fa0f5b0bbf9e.jpg",
      "category": 5
    }
  },
  {
    "model": "bucket.tooth",
    "pk": 18,
    "fields": {
      "name": "dayu360200-sharp",
      "title": "大宇360 尖 200",
      "description": "大宇360 尖 200 型号描述",
      "image": "/uploads/demo_bucket.jpg",
      "image_src": "http://sd-get.com/home/2/c/sdvaqx/resource/2020/11/03/5fa0f5b0bbf9e.jpg",
      "category": 5
    }
  },
  {
    "model": "bucket.tooth",
    "pk": 19,
    "fields": {
      "name": "dayu360100-flat",
      "title": "大宇360 平 100",
      "description": "大宇360 平 100 型号描述",
      "image": "/uploads/demo_bucket.jpg",
      "image_src": "http://sd-get.com/home/2/c/sdvaqx/resource/2020/11/03/5fa0f5b0bbf9e.jpg",
      "category": 5
    }
  },
  {
    "model": "bucket.tooth",
    "pk": 20,
    "fields": {
      "name": "dayu360200-flat",
      "title": "大宇360 平 200",
      "description": "大宇360 平 200 型号描述",
      "image": "/uploads/demo_bucket.jpg",
      "image_src": "http://sd-get.com/home/2/c/sdvaqx/resource/2020/11/03/5fa0f5b0bbf9e.jpg",
      "category": 5
    }
  },
  {
    "model": "bucket.tooth",
    "pk": 21,
    "fields": {
      "name": "dayu500100-sharp",
      "title": "大宇500 尖 100",
      "description": "大宇500 尖 100 型号描述",
      "image": "/uploads/demo_bucket.jpg",
      "image_src": "http://sd-get.com/home/2/c/sdvaqx/resource/2020/11/03/5fa0f5b0bbf9e.jpg",
      "category": 6
    }
  },
  {
    "model": "bucket.tooth",
    "pk": 22,
    "fields": {
      "name": "dayu500200-sharp",
      "title": "大宇500 尖 200",
      "description": "大宇500 尖 200 型号描述",
      "image": "/uploads/demo_bucket.jpg",
      "image_src": "http://sd-get.com/home/2/c/sdvaqx/resource/2020/11/03/5fa0f5b0bbf9e.jpg",
      "category": 6
    }
  },
  {
    "model": "bucket.tooth",
    "pk": 23,
    "fields": {
      "name": "dayu500100-flat",
      "title": "大宇500 平 100",
      "description": "大宇500 平 100 型号描述",
      "image": "/uploads/demo_bucket.jpg",
      "image_src": "http://sd-get.com/home/2/c/sdvaqx/resource/2020/11/03/5fa0f5b0bbf9e.jpg",
      "category": 6
    }
  },
  {
    "model": "bucket.tooth",
    "pk": 24,
    "fields": {
      "name": "dayu500200-flat",
      "title": "大宇500 平 200",
      "description": "大宇500 平 200 型号描述",
      "image": "/uploads/demo_bucket.jpg",
      "image_src": "http://sd-get.com/home/2/c/sdvaqx/resource/2020/11/03/5fa0f5b0bbf9e.jpg",
      "category": 6
    }
  },
  {
    "model": "bucket.tooth",
    "pk": 25,
    "fields": {
      "name": "cater312100-sharp",
      "title": "卡特312 尖 100",
      "description": "卡特312 尖 100 型号描述",
      "image": "/uploads/demo_bucket.jpg",
      "image_src": "http://sd-get.com/home/2/c/sdvaqx/resource/2020/11/03/5fa0f5b0bbf9e.jpg",
      "category": 7
    }
  },
  {
    "model": "bucket.tooth",
    "pk": 26,
    "fields": {
      "name": "cater312200-sharp",
      "title": "卡特312 尖 200",
      "description": "卡特312 尖 200 型号描述",
      "image": "/uploads/demo_bucket.jpg",
      "image_src": "http://sd-get.com/home/2/c/sdvaqx/resource/2020/11/03/5fa0f5b0bbf9e.jpg",
      "category": 7
    }
  },
  {
    "model": "bucket.tooth",
    "pk": 27,
    "fields": {
      "name": "cater312100-flat",
      "title": "卡特312 平 100",
      "description": "卡特312 平 100 型号描述",
      "image": "/uploads/demo_bucket.jpg",
      "image_src": "http://sd-get.com/home/2/c/sdvaqx/resource/2020/11/03/5fa0f5b0bbf9e.jpg",
      "category": 7
    }
  },
  {
    "model": "bucket.tooth",
    "pk": 28,
    "fields": {
      "name": "cater312200-flat",
      "title": "卡特312 平 200",
      "description": "卡特312 平 200 型号描述",
      "image": "/uploads/demo_bucket.jpg",
      "image_src": "http://sd-get.com/home/2/c/sdvaqx/resource/2020/11/03/5fa0f5b0bbf9e.jpg",
      "category": 7
    }
  },
  {
    "model": "bucket.tooth",
    "pk": 29,
    "fields": {
      "name": "cater320100-sharp",
      "title": "卡特320 尖 100",
      "description": "卡特320 尖 100 型号描述",
      "image": "/uploads/demo_bucket.jpg",
      "image_src": "http://sd-get.com/home/2/c/sdvaqx/resource/2020/11/03/5fa0f5b0bbf9e.jpg",
      "category": 8
    }
  },
  {
    "model": "bucket.tooth",
    "pk": 30,
    "fields": {
      "name": "cater320200-sharp",
      "title": "卡特320 尖 200",
      "description": "卡特320 尖 200 型号描述",
      "image": "/uploads/demo_bucket.jpg",
      "image_src": "http://sd-get.com/home/2/c/sdvaqx/resource/2020/11/03/5fa0f5b0bbf9e.jpg",
      "category": 8
    }
  },
  {
    "model": "bucket.tooth",
    "pk": 31,
    "fields": {
      "name": "cater320100-flat",
      "title": "卡特320 平 100",
      "description": "卡特320 平 100 型号描述",
      "image": "/uploads/demo_bucket.jpg",
      "image_src": "http://sd-get.com/home/2/c/sdvaqx/resource/2020/11/03/5fa0f5b0bbf9e.jpg",
      "category": 8
    }
  },
  {
    "model": "bucket.tooth",
    "pk": 32,
    "fields": {
      "name": "cater320200-flat",
      "title": "卡特320 平 200",
      "description": "卡特320 平 200 型号描述",
      "image": "/uploads/demo_bucket.jpg",
      "image_src": "http://sd-get.com/home/2/c/sdvaqx/resource/2020/11/03/5fa0f5b0bbf9e.jpg",
      "category": 8
    }
  },
  {
    "model": "bucket.tooth",
    "pk": 33,
    "fields": {
      "name": "cater325100-sharp",
      "title": "卡特325 尖 100",
      "description": "卡特325 尖 100 型号描述",
      "image": "/uploads/demo_bucket.jpg",
      "image_src": "http://sd-get.com/home/2/c/sdvaqx/resource/2020/11/03/5fa0f5b0bbf9e.jpg",
      "category": 9
    }
  },
  {
    "model": "bucket.tooth",
    "pk": 34,
    "fields": {
      "name": "cater325200-sharp",
      "title": "卡特325 尖 200",
      "description": "卡特325 尖 200 型号描述",
      "image": "/uploads/demo_bucket.jpg",
      "image_src": "http://sd-get.com/home/2/c/sdvaqx/resource/2020/11/03/5fa0f5b0bbf9e.jpg",
      "category": 9
    }
  },
  {
    "model": "bucket.tooth",
    "pk": 35,
    "fields": {
      "name": "cater325100-flat",
      "title": "卡特325 平 100",
      "description": "卡特325 平 100 型号描述",
      "image": "/uploads/demo_bucket.jpg",
      "image_src": "http://sd-get.com/home/2/c/sdvaqx/resource/2020/11/03/5fa0f5b0bbf9e.jpg",
      "category": 9
    }
  },
  {
    "model": "bucket.tooth",
    "pk": 36,
    "fields": {
      "name": "cater325200-flat",
      "title": "卡特325 平 200",
      "description": "卡特325 平 200 型号描述",
      "image": "/uploads/demo_bucket.jpg",
      "image_src": "http://sd-get.com/home/2/c/sdvaqx/resource/2020/11/03/5fa0f5b0bbf9e.jpg",
      "category": 9
    }
  },
  {
    "model": "bucket.tooth",
    "pk": 37,
    "fields": {
      "name": "cater330100-sharp",
      "title": "卡特330 尖 100",
      "description": "卡特330 尖 100 型号描述",
      "image": "/uploads/demo_bucket.jpg",
      "image_src": "http://sd-get.com/home/2/c/sdvaqx/resource/2020/11/03/5fa0f5b0bbf9e.jpg",
      "category": 10
    }
  },
  {
    "model": "bucket.tooth",
    "pk": 38,
    "fields": {
      "name": "cater330200-sharp",
      "title": "卡特330 尖 200",
      "description": "卡特330 尖 200 型号描述",
      "image": "/uploads/demo_bucket.jpg",
      "image_src": "http://sd-get.com/home/2/c/sdvaqx/resource/2020/11/03/5fa0f5b0bbf9e.jpg",
      "category": 10
    }
  },
  {
    "model": "bucket.tooth",
    "pk": 39,
    "fields": {
      "name": "cater330100-flat",
      "title": "卡特330 平 100",
      "description": "卡特330 平 100 型号描述",
      "image": "/uploads/demo_bucket.jpg",
      "image_src": "http://sd-get.com/home/2/c/sdvaqx/resource/2020/11/03/5fa0f5b0bbf9e.jpg",
      "category": 10
    }
  },
  {
    "model": "bucket.tooth",
    "pk": 40,
    "fields": {
      "name": "cater330200-flat",
      "title": "卡特330 平 200",
      "description": "卡特330 平 200 型号描述",
      "image": "/uploads/demo_bucket.jpg",
      "image_src": "http://sd-get.com/home/2/c/sdvaqx/resource/2020/11/03/5fa0f5b0bbf9e.jpg",
      "category": 10
    }
  },
  {
    "model": "bucket.tooth",
    "pk": 41,
    "fields": {
      "name": "cater345100-sharp",
      "title": "卡特345 尖 100",
      "description": "卡特345 尖 100 型号描述",
      "image": "/uploads/demo_bucket.jpg",
      "image_src": "http://sd-get.com/home/2/c/sdvaqx/resource/2020/11/03/5fa0f5b0bbf9e.jpg",
      "category": 11
    }
  },
  {
    "model": "bucket.tooth",
    "pk": 42,
    "fields": {
      "name": "cater345200-sharp",
      "title": "卡特345 尖 200",
      "description": "卡特345 尖 200 型号描述",
      "image": "/uploads/demo_bucket.jpg",
      "image_src": "http://sd-get.com/home/2/c/sdvaqx/resource/2020/11/03/5fa0f5b0bbf9e.jpg",
      "category": 11
    }
  },
  {
    "model": "bucket.tooth",
    "pk": 43,
    "fields": {
      "name": "cater345100-flat",
      "title": "卡特345 平 100",
      "description": "卡特345 平 100 型号描述",
      "image": "/uploads/demo_bucket.jpg",
      "image_src": "http://sd-get.com/home/2/c/sdvaqx/resource/2020/11/03/5fa0f5b0bbf9e.jpg",
      "category": 11
    }
  },
  {
    "model": "bucket.tooth",
    "pk": 44,
    "fields": {
      "name": "cater345200-flat",
      "title": "卡特345 平 200",
      "description": "卡特345 平 200 型号描述",
      "image": "/uploads/demo_bucket.jpg",
      "image_src": "http://sd-get.com/home/2/c/sdvaqx/resource/2020/11/03/5fa0f5b0bbf9e.jpg",
      "category": 11
    }
  },
  {
    "model": "bucket.tooth",
    "pk": 45,
    "fields": {
      "name": "hitachi-series100-sharp",
      "title": "日立系列 尖 100",
      "description": "日立系列 尖 100 型号描述",
      "image": "/uploads/demo_bucket.jpg",
      "image_src": "http://sd-get.com/home/2/c/sdvaqx/resource/2020/11/03/5fa0f5b0bbf9e.jpg",
      "category": 12
    }
  },
  {
    "model": "bucket.tooth",
    "pk": 46,
    "fields": {
      "name": "hitachi-series200-sharp",
      "title": "日立系列 尖 200",
      "description": "日立系列 尖 200 型号描述",
      "image": "/uploads/demo_bucket.jpg",
      "image_src": "http://sd-get.com/home/2/c/sdvaqx/resource/2020/11/03/5fa0f5b0bbf9e.jpg",
      "category": 12
    }
  },
  {
    "model": "bucket.tooth",
    "pk": 47,
    "fields": {
      "name": "hitachi-series100-flat",
      "title": "日立系列 平 100",
      "description": "日立系列 平 100 型号描述",
      "image": "/uploads/demo_bucket.jpg",
      "image_src": "http://sd-get.com/home/2/c/sdvaqx/resource/2020/11/03/5fa0f5b0bbf9e.jpg",
      "category": 12
    }
  },
  {
    "model": "bucket.tooth",
    "pk": 48,
    "fields": {
      "name": "hitachi-series200-flat",
      "title": "日立系列 平 200",
      "description": "日立系列 平 200 型号描述",
      "image": "/uploads/demo_bucket.jpg",
      "image_src": "http://sd-get.com/home/2/c/sdvaqx/resource/2020/11/03/5fa0f5b0bbf9e.jpg",
      "category": 12
    }
  },
  {
    "model": "bucket.tooth",
    "pk": 49,
    "fields": {
      "name": "kobelco60100-sharp",
      "title": "神钢60 尖 100",
      "description": "神钢60 尖 100 型号描述",
      "image": "/uploads/demo_bucket.jpg",
      "image_src": "http://sd-get.com/home/2/c/sdvaqx/resource/2020/11/03/5fa0f5b0bbf9e.jpg",
      "category": 13
    }
  },
  {
    "model": "bucket.tooth",
    "pk": 50,
    "fields": {
      "name": "kobelco60200-sharp",
      "title": "神钢60 尖 200",
      "description": "神钢60 尖 200 型号描述",
      "image": "/uploads/demo_bucket.jpg",
      "image_src": "http://sd-get.com/home/2/c/sdvaqx/resource/2020/11/03/5fa0f5b0bbf9e.jpg",
      "category": 13
    }
  },
  {
    "model": "bucket.tooth",
    "pk": 51,
    "fields": {
      "name": "kobelco60100-flat",
      "title": "神钢60 平 100",
      "description": "神钢60 平 100 型号描述",
      "image": "/uploads/demo_bucket.jpg",
      "image_src": "http://sd-get.com/home/2/c/sdvaqx/resource/2020/11/03/5fa0f5b0bbf9e.jpg",
      "category": 13
    }
  },
  {
    "model": "bucket.tooth",
    "pk": 52,
    "fields": {
      "name": "kobelco60200-flat",
      "title": "神钢60 平 200",
      "description": "神钢60 平 200 型号描述",
      "image": "/uploads/demo_bucket.jpg",
      "image_src": "http://sd-get.com/home/2/c/sdvaqx/resource/2020/11/03/5fa0f5b0bbf9e.jpg",
      "category": 13
    }
  },
  {
    "model": "bucket.tooth",
    "pk": 53,
    "fields": {
      "name": "kobelco200100-sharp",
      "title": "神钢200 尖 100",
      "description": "神钢200 尖 100 型号描述",
      "image": "/uploads/demo_bucket.jpg",
      "image_src": "http://sd-get.com/home/2/c/sdvaqx/resource/2020/11/03/5fa0f5b0bbf9e.jpg",
      "category": 14
    }
  },
  {
    "model": "bucket.tooth",
    "pk": 54,
    "fields": {
      "name": "kobelco200200-sharp",
      "title": "神钢200 尖 200",
      "description": "神钢200 尖 200 型号描述",
      "image": "/uploads/demo_bucket.jpg",
      "image_src": "http://sd-get.com/home/2/c/sdvaqx/resource/2020/11/03/5fa0f5b0bbf9e.jpg",
      "category": 14
    }
  },
  {
    "model": "bucket.tooth",
    "pk": 55,
    "fields": {
      "name": "kobelco200100-flat",
      "title": "神钢200 平 100",
      "description": "神钢200 平 100 型号描述",
      "image": "/uploads/demo_bucket.jpg",
      "image_src": "http://sd-get.com/home/2/c/sdvaqx/resource/2020/11/03/5fa0f5b0bbf9e.jpg",
      "category": 14
    }
  },
  {
    "model": "bucket.tooth",
    "pk": 56,
    "fields": {
      "name": "kobelco200200-flat",
      "title": "神钢200 平 200",
      "description": "神钢200 平 200 型号描述",
      "image": "/uploads/demo_bucket.jpg",
      "image_src": "http://sd-get.com/home/2/c/sdvaqx/resource/2020/11/03/5fa0f5b0bbf9e.jpg",
      "category": 14
    }
  },
  {
    "model": "bucket.tooth",
    "pk": 57,
    "fields": {
      "name": "kobelco230100-sharp",
      "title": "神钢230 尖 100",
      "description": "神钢230 尖 100 型号描述",
      "image": "/uploads/demo_bucket.jpg",
      "image_src": "http://sd-get.com/home/2/c/sdvaqx/resource/2020/11/03/5fa0f5b0bbf9e.jpg",
      "category": 15
    }
  },
  {
    "model": "bucket.tooth",
    "pk": 58,
    "fields": {
      "name": "kobelco230200-sharp",
      "title": "神钢230 尖 200",
      "description": "神钢230 尖 200 型号描述",
      "image": "/uploads/demo_bucket.jpg",
      "image_src": "http://sd-get.com/home/2/c/sdvaqx/resource/2020/11/03/5fa0f5b0bbf9e.jpg",
      "category": 15
    }
  },
  {
    "model": "bucket.tooth",
    "pk": 59,
    "fields": {
      "name": "kobelco230100-flat",
      "title": "神钢230 平 100",
      "description": "神钢230 平 100 型号描述",
      "image": "/uploads/demo_bucket.jpg",
      "image_src": "http://sd-get.com/home/2/c/sdvaqx/resource/2020/11/03/5fa0f5b0bbf9e.jpg",
      "category": 15
    }
  },
  {
    "model": "bucket.tooth",
    "pk": 60,
    "fields": {
      "name": "kobelco230200-flat",
      "title": "神钢230 平 200",
      "description": "神钢230 平 200 型号描述",
      "image": "/uploads/demo_bucket.jpg",
      "image_src": "http://sd-get.com/home/2/c/sdvaqx/resource/2020/11/03/5fa0f5b0bbf9e.jpg",
      "category": 15
    }
  },
  {
    "model": "bucket.tooth",
    "pk": 61,
    "fields": {
      "name": "kobelco350100-sharp",
      "title": "神钢350 尖 100",
      "description": "神钢350 尖 100 型号描述",
      "image": "/uploads/demo_bucket.jpg",
      "image_src": "http://sd-get.com/home/2/c/sdvaqx/resource/2020/11/03/5fa0f5b0bbf9e.jpg",
      "category": 16
    }
  },
  {
    "model": "bucket.tooth",
    "pk": 62,
    "fields": {
      "name": "kobelco350200-sharp",
      "title": "神钢350 尖 200",
      "description": "神钢350 尖 200 型号描述",
      "image": "/uploads/demo_bucket.jpg",
      "image_src": "http://sd-get.com/home/2/c/sdvaqx/resource/2020/11/03/5fa0f5b0bbf9e.jpg",
      "category": 16
    }
  },
  {
    "model": "bucket.tooth",
    "pk": 63,
    "fields": {
      "name": "kobelco350100-flat",
      "title": "神钢350 平 100",
      "description": "神钢350 平 100 型号描述",
      "image": "/uploads/demo_bucket.jpg",
      "image_src": "http://sd-get.com/home/2/c/sdvaqx/resource/2020/11/03/5fa0f5b0bbf9e.jpg",
      "category": 16
    }
  },
  {
    "model": "bucket.tooth",
    "pk": 64,
    "fields": {
      "name": "kobelco350200-flat",
      "title": "神钢350 平 200",
      "description": "神钢350 平 200 型号描述",
      "image": "/uploads/demo_bucket.jpg",
      "image_src": "http://sd-get.com/home/2/c/sdvaqx/resource/2020/11/03/5fa0f5b0bbf9e.jpg",
      "category": 16
    }
  },
  {
    "model": "bucket.tooth",
    "pk": 65,
    "fields": {
      "name": "volvo210100-sharp",
      "title": "沃210 尖 100",
      "description": "沃210 尖 100 型号描述",
      "image": "/uploads/demo_bucket.jpg",
      "image_src": "http://sd-get.com/home/2/c/sdvaqx/resource/2020/11/03/5fa0f5b0bbf9e.jpg",
      "category": 17
    }
  },
  {
    "model": "bucket.tooth",
    "pk": 66,
    "fields": {
      "name": "volvo210200-sharp",
      "title": "沃210 尖 200",
      "description": "沃210 尖 200 型号描述",
      "image": "/uploads/demo_bucket.jpg",
      "image_src": "http://sd-get.com/home/2/c/sdvaqx/resource/2020/11/03/5fa0f5b0bbf9e.jpg",
      "category": 17
    }
  },
  {
    "model": "bucket.tooth",
    "pk": 67,
    "fields": {
      "name": "volvo210100-flat",
      "title": "沃210 平 100",
      "description": "沃210 平 100 型号描述",
      "image": "/uploads/demo_bucket.jpg",
      "image_src": "http://sd-get.com/home/2/c/sdvaqx/resource/2020/11/03/5fa0f5b0bbf9e.jpg",
      "category": 17
    }
  },
  {
    "model": "bucket.tooth",
    "pk": 68,
    "fields": {
      "name": "volvo210200-flat",
      "title": "沃210 平 200",
      "description": "沃210 平 200 型号描述",
      "image": "/uploads/demo_bucket.jpg",
      "image_src": "http://sd-get.com/home/2/c/sdvaqx/resource/2020/11/03/5fa0f5b0bbf9e.jpg",
      "category": 17
    }
  },
  {
    "model": "bucket.tooth",
    "pk": 69,
    "fields": {
      "name": "volvo290100-sharp",
      "title": "沃290 尖 100",
      "description": "沃290 尖 100 型号描述",
      "image": "/uploads/demo_bucket.jpg",
      "image_src": "http://sd-get.com/home/2/c/sdvaqx/resource/2020/11/03/5fa0f5b0bbf9e.jpg",
      "category": 18
    }
  },
  {
    "model": "bucket.tooth",
    "pk": 70,
    "fields": {
      "name": "volvo290200-sharp",
      "title": "沃290 尖 200",
      "description": "沃290 尖 200 型号描述",
      "image": "/uploads/demo_bucket.jpg",
      "image_src": "http://sd-get.com/home/2/c/sdvaqx/resource/2020/11/03/5fa0f5b0bbf9e.jpg",
      "category": 18
    }
  },
  {
    "model": "bucket.tooth",
    "pk": 71,
    "fields": {
      "name": "volvo290100-flat",
      "title": "沃290 平 100",
      "description": "沃290 平 100 型号描述",
      "image": "/uploads/demo_bucket.jpg",
      "image_src": "http://sd-get.com/home/2/c/sdvaqx/resource/2020/11/03/5fa0f5b0bbf9e.jpg",
      "category": 18
    }
  },
  {
    "model": "bucket.tooth",
    "pk": 72,
    "fields": {
      "name": "volvo290200-flat",
      "title": "沃290 平 200",
      "description": "沃290 平 200 型号描述",
      "image": "/uploads/demo_bucket.jpg",
      "image_src": "http://sd-get.com/home/2/c/sdvaqx/resource/2020/11/03/5fa0f5b0bbf9e.jpg",
      "category": 18
    }
  },
  {
    "model": "bucket.tooth",
    "pk": 73,
    "fields": {
      "name": "volvo360100-sharp",
      "title": "沃360 尖 100",
      "description": "沃360 尖 100 型号描述",
      "image": "/uploads/demo_bucket.jpg",
      "image_src": "http://sd-get.com/home/2/c/sdvaqx/resource/2020/11/03/5fa0f5b0bbf9e.jpg",
      "category": 19
    }
  },
  {
    "model": "bucket.tooth",
    "pk": 74,
    "fields": {
      "name": "volvo360200-sharp",
      "title": "沃360 尖 200",
      "description": "沃360 尖 200 型号描述",
      "image": "/uploads/demo_bucket.jpg",
      "image_src": "http://sd-get.com/home/2/c/sdvaqx/resource/2020/11/03/5fa0f5b0bbf9e.jpg",
      "category": 19
    }
  },
  {
    "model": "bucket.tooth",
    "pk": 75,
    "fields": {
      "name": "volvo360100-flat",
      "title": "沃360 平 100",
      "description": "沃360 平 100 型号描述",
      "image": "/uploads/demo_bucket.jpg",
      "image_src": "http://sd-get.com/home/2/c/sdvaqx/resource/2020/11/03/5fa0f5b0bbf9e.jpg",
      "category": 19
    }
  },
  {
    "model": "bucket.tooth",
    "pk": 76,
    "fields": {
      "name": "volvo360200-flat",
      "title": "沃360 平 200",
      "description": "沃360 平 200 型号描述",
      "image": "/uploads/demo_bucket.jpg",
      "image_src": "http://sd-get.com/home/2/c/sdvaqx/resource/2020/11/03/5fa0f5b0bbf9e.jpg",
      "category": 19
    }
  },
  {
    "model": "bucket.tooth",
    "pk": 77,
    "fields": {
      "name": "hyundai-series100-sharp",
      "title": "现代系列 尖 100",
      "description": "现代系列 尖 100 型号描述",
      "image": "/uploads/demo_bucket.jpg",
      "image_src": "http://sd-get.com/home/2/c/sdvaqx/resource/2020/11/03/5fa0f5b0bbf9e.jpg",
      "category": 20
    }
  },
  {
    "model": "bucket.tooth",
    "pk": 78,
    "fields": {
      "name": "hyundai-series200-sharp",
      "title": "现代系列 尖 200",
      "description": "现代系列 尖 200 型号描述",
      "image": "/uploads/demo_bucket.jpg",
      "image_src": "http://sd-get.com/home/2/c/sdvaqx/resource/2020/11/03/5fa0f5b0bbf9e.jpg",
      "category": 20
    }
  },
  {
    "model": "bucket.tooth",
    "pk": 79,
    "fields": {
      "name": "hyundai-series100-flat",
      "title": "现代系列 平 100",
      "description": "现代系列 平 100 型号描述",
      "image": "/uploads/demo_bucket.jpg",
      "image_src": "http://sd-get.com/home/2/c/sdvaqx/resource/2020/11/03/5fa0f5b0bbf9e.jpg",
      "category": 20
    }
  },
  {
    "model": "bucket.tooth",
    "pk": 80,
    "fields": {
      "name": "hyundai-series200-flat",
      "title": "现代系列 平 200",
      "description": "现代系列 平 200 型号描述",
      "image": "/uploads/demo_bucket.jpg",
      "image_src": "http://sd-get.com/home/2/c/sdvaqx/resource/2020/11/03/5fa0f5b0bbf9e.jpg",
      "category": 20
    }
  },
  {
    "model": "bucket.tooth",
    "pk": 81,
    "fields": {
      "name": "komatsu60100-sharp",
      "title": "小松60 尖 100",
      "description": "小松60 尖 100 型号描述",
      "image": "/uploads/demo_bucket.jpg",
      "image_src": "http://sd-get.com/home/2/c/sdvaqx/resource/2020/11/03/5fa0f5b0bbf9e.jpg",
      "category": 21
    }
  },
  {
    "model": "bucket.tooth",
    "pk": 82,
    "fields": {
      "name": "komatsu60200-sharp",
      "title": "小松60 尖 200",
      "description": "小松60 尖 200 型号描述",
      "image": "/uploads/demo_bucket.jpg",
      "image_src": "http://sd-get.com/home/2/c/sdvaqx/resource/2020/11/03/5fa0f5b0bbf9e.jpg",
      "category": 21
    }
  },
  {
    "model": "bucket.tooth",
    "pk": 83,
    "fields": {
      "name": "komatsu60100-flat",
      "title": "小松60 平 100",
      "description": "小松60 平 100 型号描述",
      "image": "/uploads/demo_bucket.jpg",
      "image_src": "http://sd-get.com/home/2/c/sdvaqx/resource/2020/11/03/5fa0f5b0bbf9e.jpg",
      "category": 21
    }
  },
  {
    "model": "bucket.tooth",
    "pk": 84,
    "fields": {
      "name": "komatsu60200-flat",
      "title": "小松60 平 200",
      "description": "小松60 平 200 型号描述",
      "image": "/uploads/demo_bucket.jpg",
      "image_src": "http://sd-get.com/home/2/c/sdvaqx/resource/2020/11/03/5fa0f5b0bbf9e.jpg",
      "category": 21
    }
  },
  {
    "model": "bucket.tooth",
    "pk": 85,
    "fields": {
      "name": "komatsu100100-sharp",
      "title": "小松100 尖 100",
      "description": "小松100 尖 100 型号描述",
      "image": "/uploads/demo_bucket.jpg",
      "image_src": "http://sd-get.com/home/2/c/sdvaqx/resource/2020/11/03/5fa0f5b0bbf9e.jpg",
      "category": 22
    }
  },
  {
    "model": "bucket.tooth",
    "pk": 86,
    "fields": {
      "name": "komatsu100200-sharp",
      "title": "小松100 尖 200",
      "description": "小松100 尖 200 型号描述",
      "image": "/uploads/demo_bucket.jpg",
      "image_src": "http://sd-get.com/home/2/c/sdvaqx/resource/2020/11/03/5fa0f5b0bbf9e.jpg",
      "category": 22
    }
  },
  {
    "model": "bucket.tooth",
    "pk": 87,
    "fields": {
      "name": "komatsu100100-flat",
      "title": "小松100 平 100",
      "description": "小松100 平 100 型号描述",
      "image": "/uploads/demo_bucket.jpg",
      "image_src": "http://sd-get.com/home/2/c/sdvaqx/resource/2020/11/03/5fa0f5b0bbf9e.jpg",
      "category": 22
    }
  },
  {
    "model": "bucket.tooth",
    "pk": 88,
    "fields": {
      "name": "komatsu100200-flat",
      "title": "小松100 平 200",
      "description": "小松100 平 200 型号描述",
      "image": "/uploads/demo_bucket.jpg",
      "image_src": "http://sd-get.com/home/2/c/sdvaqx/resource/2020/11/03/5fa0f5b0bbf9e.jpg",
      "category": 22
    }
  },
  {
    "model": "bucket.tooth",
    "pk": 89,
    "fields": {
      "name": "komatsu200100-sharp",
      "title": "小松200 尖 100",
      "description": "小松200 尖 100 型号描述",
      "image": "/uploads/demo_bucket.jpg",
      "image_src": "http://sd-get.com/home/2/c/sdvaqx/resource/2020/11/03/5fa0f5b0bbf9e.jpg",
      "category": 23
    }
  },
  {
    "model": "bucket.tooth",
    "pk": 90,
    "fields": {
      "name": "komatsu200200-sharp",
      "title": "小松200 尖 200",
      "description": "小松200 尖 200 型号描述",
      "image": "/uploads/demo_bucket.jpg",
      "image_src": "http://sd-get.com/home/2/c/sdvaqx/resource/2020/11/03/5fa0f5b0bbf9e.jpg",
      "category": 23
    }
  },
  {
    "model": "bucket.tooth",
    "pk": 91,
    "fields": {
      "name": "komatsu200100-flat",
      "title": "小松200 平 100",
      "description": "小松200 平 100 型号描述",
      "image": "/uploads/demo_bucket.jpg",
      "image_src": "http://sd-get.com/home/2/c/sdvaqx/resource/2020/11/03/5fa0f5b0bbf9e.jpg",
      "category": 23
    }
  },
  {
    "model": "bucket.tooth",
    "pk": 92,
    "fields": {
      "name": "komatsu200200-flat",
      "title": "小松200 平 200",
      "description": "小松200 平 200 型号描述",
      "image": "/uploads/demo_bucket.jpg",
      "image_src": "http://sd-get.com/home/2/c/sdvaqx/resource/2020/11/03/5fa0f5b0bbf9e.jpg",
      "category": 23
    }
  },
  {
    "model": "bucket.tooth",
    "pk": 93,
    "fields": {
      "name": "komatsu300100-sharp",
      "title": "小松300 尖 100",
      "description": "小松300 尖 100 型号描述",
      "image": "/uploads/demo_bucket.jpg",
      "image_src": "http://sd-get.com/home/2/c/sdvaqx/resource/2020/11/03/5fa0f5b0bbf9e.jpg",
      "category": 24
    }
  },
  {
    "model": "bucket.tooth",
    "pk": 94,
    "fields": {
      "name": "komatsu300200-sharp",
      "title": "小松300 尖 200",
      "description": "小松300 尖 200 型号描述",
      "image": "/uploads/demo_bucket.jpg",
      "image_src": "http://sd-get.com/home/2/c/sdvaqx/resource/2020/11/03/5fa0f5b0bbf9e.jpg",
      "category": 24
    }
  },
  {
    "model": "bucket.tooth",
    "pk": 95,
    "fields": {
      "name": "komatsu300100-flat",
      "title": "小松300 平 100",
      "description": "小松300 平 100 型号描述",
      "image": "/uploads/demo_bucket.jpg",
      "image_src": "http://sd-get.com/home/2/c/sdvaqx/resource/2020/11/03/5fa0f5b0bbf9e.jpg",
      "category": 24
    }
  },
  {
    "model": "bucket.tooth",
    "pk": 96,
    "fields": {
      "name": "komatsu300200-flat",
      "title": "小松300 平 200",
      "description": "小松300 平 200 型号描述",
      "image": "/uploads/demo_bucket.jpg",
      "image_src": "http://sd-get.com/home/2/c/sdvaqx/resource/2020/11/03/5fa0f5b0bbf9e.jpg",
      "category": 24
    }
  },
  {
    "model": "bucket.tooth",
    "pk": 97,
    "fields": {
      "name": "komatsu400100-sharp",
      "title": "小松400 尖 100",
      "description": "小松400 尖 100 型号描述",
      "image": "/uploads/demo_bucket.jpg",
      "image_src": "http://sd-get.com/home/2/c/sdvaqx/resource/2020/11/03/5fa0f5b0bbf9e.jpg",
      "category": 25
    }
  },
  {
    "model": "bucket.tooth",
    "pk": 98,
    "fields": {
      "name": "komatsu400200-sharp",
      "title": "小松400 尖 200",
      "description": "小松400 尖 200 型号描述",
      "image": "/uploads/demo_bucket.jpg",
      "image_src": "http://sd-get.com/home/2/c/sdvaqx/resource/2020/11/03/5fa0f5b0bbf9e.jpg",
      "category": 25
    }
  },
  {
    "model": "bucket.tooth",
    "pk": 99,
    "fields": {
      "name": "komatsu400100-flat",
      "title": "小松400 平 100",
      "description": "小松400 平 100 型号描述",
      "image": "/uploads/demo_bucket.jpg",
      "image_src": "http://sd-get.com/home/2/c/sdvaqx/resource/2020/11/03/5fa0f5b0bbf9e.jpg",
      "category": 25
    }
  },
  {
    "model": "bucket.tooth",
    "pk": 100,
    "fields": {
      "name": "komatsu400200-flat",
      "title": "小松400 平 200",
      "description": "小松400 平 200 型号描述",
      "image": "/uploads/demo_bucket.jpg",
      "image_src": "http://sd-get.com/home/2/c/sdvaqx/resource/2020/11/03/5fa0f5b0bbf9e.jpg",
      "category": 25
    }
  },
  {
    "model": "bucket.tooth",
    "pk": 101,
    "fields": {
      "name": "xiaozi100-sharp",
      "title": "销子 尖 100",
      "description": "销子 尖 100 型号描述",
      "image": "/uploads/demo_bucket.jpg",
      "image_src": "http://sd-get.com/home/2/c/sdvaqx/resource/2020/11/03/5fa0f5b0bbf9e.jpg",
      "category": 26
    }
  },
  {
    "model": "bucket.tooth",
    "pk": 102,
    "fields": {
      "name": "xiaozi200-sharp",
      "title": "销子 尖 200",
      "description": "销子 尖 200 型号描述",
      "image": "/uploads/demo_bucket.jpg",
      "image_src": "http://sd-get.com/home/2/c/sdvaqx/resource/2020/11/03/5fa0f5b0bbf9e.jpg",
      "category": 26
    }
  },
  {
    "model": "bucket.tooth",
    "pk": 103,
    "fields": {
      "name": "xiaozi100-flat",
      "title": "销子 平 100",
      "description": "销子 平 100 型号描述",
      "image": "/uploads/demo_bucket.jpg",
      "image_src": "http://sd-get.com/home/2/c/sdvaqx/resource/2020/11/03/5fa0f5b0bbf9e.jpg",
      "category": 26
    }
  },
  {
    "model": "bucket.tooth",
    "pk": 104,
    "fields": {
      "name": "xiaozi200-flat",
      "title": "销子 平 200",
      "description": "销子 平 200 型号描述",
      "image": "/uploads/demo_bucket.jpg",
      "image_src": "http://sd-get.com/home/2/c/sdvaqx/resource/2020/11/03/5fa0f5b0bbf9e.jpg",
      "category": 26
    }
  },
  {
    "model": "bucket.tooth",
    "pk": 105,
    "fields": {
      "name": "combined100-sharp",
      "title": "组合 尖 100",
      "description": "组合 尖 100 型号描述",
      "image": "/uploads/demo_bucket.jpg",
      "image_src": "http://sd-get.com/home/2/c/sdvaqx/resource/2020/11/03/5fa0f5b0bbf9e.jpg",
      "category": 27
    }
  },
  {
    "model": "bucket.tooth",
    "pk": 106,
    "fields": {
      "name": "combined200-sharp",
      "title": "组合 尖 200",
      "description": "组合 尖 200 型号描述",
      "image": "/uploads/demo_bucket.jpg",
      "image_src": "http://sd-get.com/home/2/c/sdvaqx/resource/2020/11/03/5fa0f5b0bbf9e.jpg",
      "category": 27
    }
  },
  {
    "model": "bucket.tooth",
    "pk": 107,
    "fields": {
      "name": "combined100-flat",
      "title": "组合 平 100",
      "description": "组合 平 100 型号描述",
      "image": "/uploads/demo_bucket.jpg",
      "image_src": "http://sd-get.com/home/2/c/sdvaqx/resource/2020/11/03/5fa0f5b0bbf9e.jpg",
      "category": 27
    }
  },
  {
    "model": "bucket.tooth",
    "pk": 108,
    "fields": {
      "name": "combined200-flat",
      "title": "组合 平 200",
      "description": "组合 平 200 型号描述",
      "image": "/uploads/demo_bucket.jpg",
      "image_src": "http://sd-get.com/home/2/c/sdvaqx/resource/2020/11/03/5fa0f5b0bbf9e.jpg",
      "category": 27
    }
  }
]